py_db_migrate/__init__.py
py_db_migrate/configuration.py
py_db_migrate/database/__init__.py
py_db_migrate/database/postgresql.py
py_db_migrate/logger.py
py_db_migrate/main.py
py_db_migrate/service/__init__.py
py_db_migrate/service/migration_down.py
py_db_migrate/service/migration_files.py
py_db_migrate/service/migration_up.py
py_db_migrate/service/migration_validator.py
py_db_migrate/service/service.py
py_db_migrate/service/start.py
py_db_migrate/service/utils.py
py_db_migrate-0.3.1.dist-info/LICENSE
py_db_migrate-0.3.1.dist-info/METADATA
py_db_migrate-0.3.1.dist-info/WHEEL
py_db_migrate-0.3.1.dist-info/entry_points.txt
py_db_migrate-0.3.1.dist-info/RECORD
