Metadata-Version: 2.1
Name: py-db-migrate
Version: 0.3.1
Summary: The CLI application for managing SQL migrations.
Home-page: https://github.com/akemalyildirim1/py-db-migrate
Keywords: psql,sql,migration,typer,python
Author: akemalyildirim1
Author-email: akemalyildirim1@gmail.com
Requires-Python: >=3.11,<4.0
Classifier: Programming Language :: Python :: 3
Classifier: Programming Language :: Python :: 3.11
Requires-Dist: aiofiles (>=23.2.1,<24.0.0)
Requires-Dist: asyncpg (>=0.28.0,<0.29.0)
Requires-Dist: overrides (>=7.4.0,<8.0.0)
Requires-Dist: pydantic (>=2.3.0,<3.0.0)
Requires-Dist: pypika (>=0.48.9,<0.49.0)
Requires-Dist: pyyaml (>=6.0.1,<7.0.0)
Requires-Dist: typer[all] (>=0.9.0,<0.10.0)
Project-URL: Issue tracker, https://github.com/akemalyildirim1/py-db-migrate/issues
Project-URL: Repository, https://github.com/akemalyildirim1/py-db-migrate
